testpypiproject123/__init__.py
testpypiproject123/your_module.py
testpypiproject123-3.5.dist-info/LICENSE
testpypiproject123-3.5.dist-info/METADATA
testpypiproject123-3.5.dist-info/WHEEL
testpypiproject123-3.5.dist-info/top_level.txt
testpypiproject123-3.5.dist-info/RECORD
